jubox/__init__.py
jubox/_version.py
jubox/base.py
jubox/cell.py
jubox/notebook.py
jubox/utils.py
jubox/builtin/__init__.py
jubox/builtin/notebook.py
jubox/cell/__init__.py
jubox/cell/accessors.py
jubox/cell/base.py
jubox/cell/cell.py
jubox/cell/code.py
jubox/cell/code_cell.py
jubox/cell/markdown.py
jubox/cell/markdown_cell.py
jubox/cell/raw.py
jubox/cell/raw_cell.py
jubox/notebook/__init__.py
jubox/notebook/accessors.py
jubox/notebook/notebook.py
jubox/test/__init__.py
jubox/test/conftest.py
jubox/test/builtin/__init__.py
jubox/test/builtin/test_run_notebook.py
jubox/test/cell/__init__.py
jubox/test/cell/test_convert.py
jubox/test/cell/test_modification.py
jubox/test/cell/code/__init__.py
jubox/test/cell/code/test_creation.py
jubox/test/cell/code/test_execution.py
jubox/test/cell/code/test_modification.py
jubox/test/cell/code/test_output.py
jubox/test/cell/creation/__init__.py
jubox/test/cell/creation/test_from_cells.py
jubox/test/cell/creation/test_from_nodes.py
jubox/test/cell/creation/test_generic.py
jubox/test/cell/markdown/__init__.py
jubox/test/cell/raw/__init__.py
jubox/test/examples/__init__.py
jubox/test/examples/test_pipeline.py
jubox/test/helpers/__init__.py
jubox/test/helpers/utils.py
jubox/test/notebook/__init__.py
jubox/test/notebook/test_creation.py
jubox/test/notebook/test_execute.py
jubox/test/notebook/test_get.py
jubox/test/notebook/test_io.py
jubox/test/notebook/test_item.py
jubox/test/notebook/test_magic.py
jubox/test/notebook/accessors/__init__.py
jubox/test/notebook/accessors/test_cells.py
jubox/test/test_files/nb_simple.ipynb
jubox/test/test_files/nb_task.ipynb
jubox/test/test_files/nb_unrun.ipynb
jubox/test/test_files/nb_with_celltypes.ipynb
jubox/test/test_files/nb_with_error.ipynb
jubox/test/test_files/nb_with_outputs.ipynb
jubox/test/test_files/nb_with_tags.ipynb
jubox/test/test_files/notebook_with_outputs.ipynb
jubox/utils/__init__.py
jubox/utils/accessor.py
jubox/utils/html.py
jubox/utils/match_node.py
jubox/utils/node.py
JuBox-0.4.0.dist-info/LICENSE
JuBox-0.4.0.dist-info/METADATA
JuBox-0.4.0.dist-info/WHEEL
JuBox-0.4.0.dist-info/top_level.txt
JuBox-0.4.0.dist-info/RECORD
