Metadata-Version: 2.1
Name: JuBox
Version: 0.4.0
Summary: Object oriented interface to Jupyter Notebook
Home-page: UNKNOWN
Author: Mikael Koli
Author-email: koli.mikael@gmail.com
License: UNKNOWN
Platform: UNKNOWN
Classifier: Programming Language :: Python :: 3
Classifier: License :: OSI Approved :: MIT License
Classifier: Operating System :: OS Independent
Requires-Python: >=3.6
